{
    "spotlight_starttime_hours": "7",
    "spotlight_intensity_2": "75",
    "germination_stage": "3",
    "date_modified": "25-08-2018 15:56:00",
    "spotlight_mode": "auto",
    "session_id": "t2p6qrhmn2k6qllltoktoao501",
    "spotlight_intensity_1": "25",
    "camera_activity": "false",
    "configuration_name": "Default Settings",
    "specie_scheme": "fruiting",
    "agriculture_mode": "soil",
    "timezone": "Europe/Brussels",
    "spotlight_activity": "true",
    "spotlight_starttime_minutes": "30"
}